{
    "nodos": {
        "extremos": [
            [
                24,
                223
            ],
            [
                189,
                236
            ],
            [
                229,
                51
            ],
            [
                238,
                207
            ]
        ],
        "bifurcaciones": [
            [
                17,
                133
            ],
            [
                18,
                133
            ],
            [
                18,
                134
            ],
            [
                191,
                157
            ],
            [
                191,
                158
            ],
            [
                191,
                159
            ]
        ],
        "trifurcaciones": [
            [
                192,
                158
            ]
        ],
        "intermedios": [
            [
                8,
                112
            ],
            [
                12,
                128
            ],
            [
                19,
                120
            ],
            [
                20,
                146
            ],
            [
                23,
                157
            ],
            [
                27,
                166
            ],
            [
                30,
                179
            ],
            [
                32,
                208
            ],
            [
                38,
                71
            ],
            [
                50,
                80
            ],
            [
                63,
                58
            ],
            [
                75,
                73
            ],
            [
                88,
                52
            ],
            [
                100,
                72
            ],
            [
                113,
                49
            ],
            [
                125,
                67
            ],
            [
                138,
                48
            ],
            [
                150,
                69
            ],
            [
                159,
                84
            ],
            [
                161,
                107
            ],
            [
                169,
                123
            ],
            [
                180,
                137
            ],
            [
                186,
                177
            ],
            [
                188,
                232
            ],
            [
                191,
                162
            ],
            [
                196,
                192
            ],
            [
                201,
                200
            ],
            [
                210,
                173
            ],
            [
                215,
                207
            ],
            [
                220,
                62
            ],
            [
                230,
                213
            ]
        ]
    }
}