{
    "nodos": {
        "extremos": [
            [
                24,
                223
            ],
            [
                189,
                236
            ],
            [
                229,
                51
            ],
            [
                238,
                207
            ]
        ],
        "bifurcaciones": [
            [
                17,
                133
            ],
            [
                18,
                133
            ],
            [
                18,
                134
            ],
            [
                191,
                157
            ],
            [
                191,
                158
            ],
            [
                191,
                159
            ]
        ],
        "trifurcaciones": [
            [
                192,
                158
            ]
        ],
        "intermedios": [
            [
                8,
                112
            ],
            [
                8,
                113
            ],
            [
                8,
                114
            ],
            [
                8,
                115
            ],
            [
                8,
                116
            ],
            [
                8,
                117
            ],
            [
                9,
                109
            ],
            [
                9,
                110
            ],
            [
                9,
                111
            ],
            [
                9,
                118
            ],
            [
                9,
                119
            ],
            [
                9,
                120
            ],
            [
                10,
                107
            ],
            [
                10,
                108
            ],
            [
                10,
                121
            ],
            [
                10,
                122
            ],
            [
                10,
                123
            ],
            [
                10,
                124
            ],
            [
                11,
                104
            ],
            [
                11,
                105
            ],
            [
                11,
                106
            ],
            [
                11,
                125
            ],
            [
                11,
                126
            ],
            [
                12,
                103
            ],
            [
                12,
                127
            ],
            [
                12,
                128
            ],
            [
                13,
                100
            ],
            [
                13,
                101
            ],
            [
                13,
                102
            ],
            [
                13,
                129
            ],
            [
                13,
                130
            ],
            [
                14,
                98
            ],
            [
                14,
                99
            ],
            [
                14,
                131
            ],
            [
                15,
                96
            ],
            [
                15,
                97
            ],
            [
                15,
                132
            ],
            [
                16,
                93
            ],
            [
                16,
                94
            ],
            [
                16,
                95
            ],
            [
                16,
                132
            ],
            [
                17,
                92
            ],
            [
                18,
                91
            ],
            [
                18,
                135
            ],
            [
                18,
                136
            ],
            [
                18,
                137
            ],
            [
                19,
                89
            ],
            [
                19,
                90
            ],
            [
                19,
                118
            ],
            [
                19,
                119
            ],
            [
                19,
                120
            ],
            [
                19,
                121
            ],
            [
                19,
                122
            ],
            [
                19,
                123
            ],
            [
                19,
                124
            ],
            [
                19,
                125
            ],
            [
                19,
                126
            ],
            [
                19,
                127
            ],
            [
                19,
                128
            ],
            [
                19,
                129
            ],
            [
                19,
                130
            ],
            [
                19,
                131
            ],
            [
                19,
                132
            ],
            [
                19,
                138
            ],
            [
                19,
                139
            ],
            [
                19,
                140
            ],
            [
                19,
                141
            ],
            [
                20,
                88
            ],
            [
                20,
                115
            ],
            [
                20,
                116
            ],
            [
                20,
                117
            ],
            [
                20,
                142
            ],
            [
                20,
                143
            ],
            [
                20,
                144
            ],
            [
                20,
                145
            ],
            [
                20,
                146
            ],
            [
                21,
                86
            ],
            [
                21,
                87
            ],
            [
                21,
                111
            ],
            [
                21,
                112
            ],
            [
                21,
                113
            ],
            [
                21,
                114
            ],
            [
                21,
                147
            ],
            [
                21,
                148
            ],
            [
                21,
                149
            ],
            [
                21,
                150
            ],
            [
                21,
                151
            ],
            [
                22,
                85
            ],
            [
                22,
                108
            ],
            [
                22,
                109
            ],
            [
                22,
                110
            ],
            [
                22,
                152
            ],
            [
                22,
                153
            ],
            [
                22,
                154
            ],
            [
                22,
                155
            ],
            [
                23,
                84
            ],
            [
                23,
                105
            ],
            [
                23,
                106
            ],
            [
                23,
                107
            ],
            [
                23,
                156
            ],
            [
                23,
                157
            ],
            [
                23,
                158
            ],
            [
                24,
                82
            ],
            [
                24,
                83
            ],
            [
                24,
                103
            ],
            [
                24,
                104
            ],
            [
                24,
                159
            ],
            [
                24,
                160
            ],
            [
                24,
                222
            ],
            [
                25,
                81
            ],
            [
                25,
                102
            ],
            [
                25,
                161
            ],
            [
                25,
                162
            ],
            [
                25,
                220
            ],
            [
                25,
                221
            ],
            [
                26,
                80
            ],
            [
                26,
                100
            ],
            [
                26,
                101
            ],
            [
                26,
                163
            ],
            [
                26,
                164
            ],
            [
                26,
                165
            ],
            [
                26,
                219
            ],
            [
                27,
                79
            ],
            [
                27,
                98
            ],
            [
                27,
                99
            ],
            [
                27,
                166
            ],
            [
                27,
                167
            ],
            [
                27,
                168
            ],
            [
                27,
                169
            ],
            [
                27,
                218
            ],
            [
                28,
                79
            ],
            [
                28,
                96
            ],
            [
                28,
                97
            ],
            [
                28,
                170
            ],
            [
                28,
                171
            ],
            [
                28,
                172
            ],
            [
                28,
                173
            ],
            [
                28,
                217
            ],
            [
                29,
                78
            ],
            [
                29,
                94
            ],
            [
                29,
                95
            ],
            [
                29,
                174
            ],
            [
                29,
                175
            ],
            [
                29,
                215
            ],
            [
                29,
                216
            ],
            [
                30,
                77
            ],
            [
                30,
                93
            ],
            [
                30,
                176
            ],
            [
                30,
                177
            ],
            [
                30,
                178
            ],
            [
                30,
                179
            ],
            [
                30,
                180
            ],
            [
                30,
                214
            ],
            [
                31,
                76
            ],
            [
                31,
                92
            ],
            [
                31,
                181
            ],
            [
                31,
                182
            ],
            [
                31,
                183
            ],
            [
                31,
                184
            ],
            [
                31,
                210
            ],
            [
                31,
                211
            ],
            [
                31,
                212
            ],
            [
                31,
                213
            ],
            [
                32,
                76
            ],
            [
                32,
                91
            ],
            [
                32,
                185
            ],
            [
                32,
                186
            ],
            [
                32,
                187
            ],
            [
                32,
                188
            ],
            [
                32,
                189
            ],
            [
                32,
                190
            ],
            [
                32,
                204
            ],
            [
                32,
                205
            ],
            [
                32,
                206
            ],
            [
                32,
                207
            ],
            [
                32,
                208
            ],
            [
                32,
                209
            ],
            [
                33,
                75
            ],
            [
                33,
                90
            ],
            [
                33,
                191
            ],
            [
                33,
                192
            ],
            [
                33,
                193
            ],
            [
                33,
                194
            ],
            [
                33,
                195
            ],
            [
                33,
                196
            ],
            [
                33,
                197
            ],
            [
                33,
                198
            ],
            [
                33,
                199
            ],
            [
                33,
                200
            ],
            [
                33,
                201
            ],
            [
                33,
                202
            ],
            [
                33,
                203
            ],
            [
                34,
                74
            ],
            [
                34,
                89
            ],
            [
                35,
                73
            ],
            [
                35,
                89
            ],
            [
                36,
                73
            ],
            [
                36,
                88
            ],
            [
                37,
                72
            ],
            [
                37,
                87
            ],
            [
                38,
                71
            ],
            [
                38,
                87
            ],
            [
                39,
                71
            ],
            [
                39,
                86
            ],
            [
                40,
                70
            ],
            [
                40,
                86
            ],
            [
                41,
                69
            ],
            [
                41,
                85
            ],
            [
                42,
                69
            ],
            [
                42,
                84
            ],
            [
                43,
                68
            ],
            [
                43,
                84
            ],
            [
                44,
                67
            ],
            [
                44,
                83
            ],
            [
                45,
                66
            ],
            [
                45,
                83
            ],
            [
                46,
                66
            ],
            [
                46,
                82
            ],
            [
                47,
                65
            ],
            [
                47,
                82
            ],
            [
                48,
                65
            ],
            [
                48,
                81
            ],
            [
                49,
                64
            ],
            [
                49,
                80
            ],
            [
                50,
                64
            ],
            [
                50,
                80
            ],
            [
                51,
                63
            ],
            [
                51,
                80
            ],
            [
                52,
                63
            ],
            [
                52,
                80
            ],
            [
                53,
                62
            ],
            [
                53,
                79
            ],
            [
                54,
                62
            ],
            [
                54,
                79
            ],
            [
                55,
                62
            ],
            [
                55,
                79
            ],
            [
                56,
                61
            ],
            [
                56,
                78
            ],
            [
                57,
                61
            ],
            [
                57,
                78
            ],
            [
                58,
                60
            ],
            [
                58,
                77
            ],
            [
                59,
                60
            ],
            [
                59,
                77
            ],
            [
                60,
                59
            ],
            [
                60,
                77
            ],
            [
                61,
                59
            ],
            [
                61,
                76
            ],
            [
                62,
                59
            ],
            [
                62,
                76
            ],
            [
                63,
                58
            ],
            [
                63,
                76
            ],
            [
                64,
                58
            ],
            [
                64,
                75
            ],
            [
                65,
                58
            ],
            [
                65,
                75
            ],
            [
                66,
                57
            ],
            [
                66,
                75
            ],
            [
                67,
                57
            ],
            [
                67,
                74
            ],
            [
                68,
                57
            ],
            [
                68,
                74
            ],
            [
                69,
                56
            ],
            [
                69,
                74
            ],
            [
                70,
                56
            ],
            [
                70,
                74
            ],
            [
                71,
                56
            ],
            [
                71,
                74
            ],
            [
                72,
                55
            ],
            [
                72,
                74
            ],
            [
                73,
                55
            ],
            [
                73,
                74
            ],
            [
                74,
                55
            ],
            [
                74,
                73
            ],
            [
                75,
                54
            ],
            [
                75,
                73
            ],
            [
                76,
                54
            ],
            [
                76,
                73
            ],
            [
                77,
                54
            ],
            [
                77,
                73
            ],
            [
                78,
                54
            ],
            [
                78,
                73
            ],
            [
                79,
                53
            ],
            [
                79,
                73
            ],
            [
                80,
                53
            ],
            [
                80,
                73
            ],
            [
                81,
                53
            ],
            [
                81,
                73
            ],
            [
                82,
                52
            ],
            [
                82,
                73
            ],
            [
                83,
                52
            ],
            [
                83,
                73
            ],
            [
                84,
                52
            ],
            [
                84,
                73
            ],
            [
                85,
                52
            ],
            [
                85,
                73
            ],
            [
                86,
                52
            ],
            [
                86,
                73
            ],
            [
                87,
                52
            ],
            [
                87,
                73
            ],
            [
                88,
                52
            ],
            [
                88,
                73
            ],
            [
                89,
                52
            ],
            [
                89,
                73
            ],
            [
                90,
                52
            ],
            [
                90,
                73
            ],
            [
                91,
                52
            ],
            [
                91,
                73
            ],
            [
                92,
                52
            ],
            [
                92,
                73
            ],
            [
                93,
                52
            ],
            [
                93,
                73
            ],
            [
                94,
                53
            ],
            [
                94,
                73
            ],
            [
                95,
                53
            ],
            [
                95,
                73
            ],
            [
                96,
                53
            ],
            [
                96,
                72
            ],
            [
                97,
                53
            ],
            [
                97,
                72
            ],
            [
                98,
                53
            ],
            [
                98,
                72
            ],
            [
                99,
                52
            ],
            [
                99,
                72
            ],
            [
                100,
                52
            ],
            [
                100,
                72
            ],
            [
                101,
                52
            ],
            [
                101,
                72
            ],
            [
                102,
                52
            ],
            [
                102,
                73
            ],
            [
                103,
                51
            ],
            [
                103,
                73
            ],
            [
                104,
                51
            ],
            [
                104,
                73
            ],
            [
                105,
                51
            ],
            [
                105,
                73
            ],
            [
                106,
                51
            ],
            [
                106,
                72
            ],
            [
                107,
                51
            ],
            [
                107,
                72
            ],
            [
                108,
                50
            ],
            [
                108,
                72
            ],
            [
                109,
                50
            ],
            [
                109,
                72
            ],
            [
                110,
                50
            ],
            [
                110,
                72
            ],
            [
                111,
                49
            ],
            [
                111,
                72
            ],
            [
                112,
                49
            ],
            [
                112,
                72
            ],
            [
                113,
                49
            ],
            [
                113,
                72
            ],
            [
                114,
                48
            ],
            [
                114,
                72
            ],
            [
                115,
                48
            ],
            [
                115,
                72
            ],
            [
                116,
                48
            ],
            [
                116,
                71
            ],
            [
                117,
                47
            ],
            [
                117,
                71
            ],
            [
                118,
                47
            ],
            [
                118,
                71
            ],
            [
                119,
                47
            ],
            [
                119,
                70
            ],
            [
                120,
                46
            ],
            [
                120,
                70
            ],
            [
                121,
                46
            ],
            [
                121,
                69
            ],
            [
                122,
                46
            ],
            [
                122,
                69
            ],
            [
                123,
                46
            ],
            [
                123,
                68
            ],
            [
                124,
                46
            ],
            [
                124,
                68
            ],
            [
                125,
                46
            ],
            [
                125,
                67
            ],
            [
                126,
                46
            ],
            [
                126,
                66
            ],
            [
                127,
                46
            ],
            [
                127,
                66
            ],
            [
                128,
                46
            ],
            [
                128,
                65
            ],
            [
                129,
                46
            ],
            [
                129,
                65
            ],
            [
                130,
                46
            ],
            [
                130,
                65
            ],
            [
                131,
                47
            ],
            [
                131,
                65
            ],
            [
                132,
                47
            ],
            [
                132,
                64
            ],
            [
                133,
                47
            ],
            [
                133,
                64
            ],
            [
                134,
                47
            ],
            [
                134,
                63
            ],
            [
                135,
                47
            ],
            [
                135,
                63
            ],
            [
                136,
                47
            ],
            [
                136,
                63
            ],
            [
                137,
                47
            ],
            [
                137,
                63
            ],
            [
                138,
                48
            ],
            [
                138,
                63
            ],
            [
                139,
                48
            ],
            [
                139,
                63
            ],
            [
                140,
                48
            ],
            [
                140,
                64
            ],
            [
                141,
                48
            ],
            [
                141,
                64
            ],
            [
                142,
                48
            ],
            [
                142,
                64
            ],
            [
                143,
                48
            ],
            [
                143,
                65
            ],
            [
                144,
                48
            ],
            [
                144,
                66
            ],
            [
                145,
                48
            ],
            [
                145,
                66
            ],
            [
                146,
                49
            ],
            [
                146,
                66
            ],
            [
                147,
                49
            ],
            [
                147,
                67
            ],
            [
                148,
                49
            ],
            [
                148,
                67
            ],
            [
                149,
                49
            ],
            [
                149,
                68
            ],
            [
                150,
                49
            ],
            [
                150,
                69
            ],
            [
                151,
                49
            ],
            [
                151,
                70
            ],
            [
                152,
                50
            ],
            [
                152,
                70
            ],
            [
                153,
                50
            ],
            [
                153,
                71
            ],
            [
                154,
                50
            ],
            [
                154,
                72
            ],
            [
                155,
                50
            ],
            [
                155,
                73
            ],
            [
                155,
                74
            ],
            [
                156,
                50
            ],
            [
                156,
                75
            ],
            [
                156,
                76
            ],
            [
                157,
                50
            ],
            [
                157,
                77
            ],
            [
                157,
                78
            ],
            [
                157,
                79
            ],
            [
                158,
                50
            ],
            [
                158,
                80
            ],
            [
                158,
                81
            ],
            [
                158,
                82
            ],
            [
                159,
                50
            ],
            [
                159,
                83
            ],
            [
                159,
                84
            ],
            [
                159,
                85
            ],
            [
                159,
                86
            ],
            [
                159,
                87
            ],
            [
                159,
                88
            ],
            [
                159,
                89
            ],
            [
                159,
                90
            ],
            [
                159,
                91
            ],
            [
                159,
                92
            ],
            [
                159,
                93
            ],
            [
                159,
                94
            ],
            [
                159,
                95
            ],
            [
                159,
                96
            ],
            [
                159,
                97
            ],
            [
                159,
                98
            ],
            [
                159,
                99
            ],
            [
                159,
                100
            ],
            [
                159,
                101
            ],
            [
                159,
                102
            ],
            [
                160,
                51
            ],
            [
                160,
                103
            ],
            [
                160,
                104
            ],
            [
                160,
                105
            ],
            [
                160,
                106
            ],
            [
                161,
                51
            ],
            [
                161,
                107
            ],
            [
                161,
                108
            ],
            [
                161,
                109
            ],
            [
                162,
                51
            ],
            [
                162,
                110
            ],
            [
                162,
                111
            ],
            [
                162,
                112
            ],
            [
                163,
                51
            ],
            [
                163,
                113
            ],
            [
                163,
                114
            ],
            [
                163,
                115
            ],
            [
                164,
                52
            ],
            [
                164,
                116
            ],
            [
                164,
                117
            ],
            [
                165,
                52
            ],
            [
                165,
                118
            ],
            [
                165,
                119
            ],
            [
                165,
                120
            ],
            [
                166,
                52
            ],
            [
                166,
                121
            ],
            [
                167,
                53
            ],
            [
                167,
                122
            ],
            [
                168,
                53
            ],
            [
                168,
                123
            ],
            [
                169,
                53
            ],
            [
                169,
                123
            ],
            [
                170,
                53
            ],
            [
                170,
                124
            ],
            [
                171,
                53
            ],
            [
                171,
                125
            ],
            [
                172,
                53
            ],
            [
                172,
                126
            ],
            [
                173,
                53
            ],
            [
                173,
                127
            ],
            [
                174,
                53
            ],
            [
                174,
                128
            ],
            [
                175,
                52
            ],
            [
                175,
                129
            ],
            [
                175,
                130
            ],
            [
                176,
                52
            ],
            [
                176,
                131
            ],
            [
                177,
                52
            ],
            [
                177,
                132
            ],
            [
                177,
                133
            ],
            [
                178,
                52
            ],
            [
                178,
                134
            ],
            [
                179,
                51
            ],
            [
                179,
                135
            ],
            [
                180,
                51
            ],
            [
                180,
                136
            ],
            [
                180,
                137
            ],
            [
                181,
                51
            ],
            [
                181,
                138
            ],
            [
                181,
                139
            ],
            [
                182,
                51
            ],
            [
                182,
                140
            ],
            [
                183,
                50
            ],
            [
                183,
                141
            ],
            [
                183,
                142
            ],
            [
                184,
                50
            ],
            [
                184,
                143
            ],
            [
                184,
                144
            ],
            [
                185,
                50
            ],
            [
                185,
                145
            ],
            [
                185,
                146
            ],
            [
                185,
                179
            ],
            [
                185,
                180
            ],
            [
                185,
                181
            ],
            [
                185,
                182
            ],
            [
                185,
                183
            ],
            [
                185,
                184
            ],
            [
                185,
                185
            ],
            [
                186,
                49
            ],
            [
                186,
                147
            ],
            [
                186,
                148
            ],
            [
                186,
                177
            ],
            [
                186,
                178
            ],
            [
                186,
                186
            ],
            [
                187,
                49
            ],
            [
                187,
                149
            ],
            [
                187,
                175
            ],
            [
                187,
                176
            ],
            [
                187,
                187
            ],
            [
                187,
                222
            ],
            [
                187,
                223
            ],
            [
                187,
                224
            ],
            [
                187,
                225
            ],
            [
                187,
                226
            ],
            [
                187,
                227
            ],
            [
                187,
                228
            ],
            [
                187,
                229
            ],
            [
                188,
                48
            ],
            [
                188,
                150
            ],
            [
                188,
                173
            ],
            [
                188,
                174
            ],
            [
                188,
                188
            ],
            [
                188,
                220
            ],
            [
                188,
                221
            ],
            [
                188,
                230
            ],
            [
                188,
                231
            ],
            [
                188,
                232
            ],
            [
                188,
                233
            ],
            [
                189,
                48
            ],
            [
                189,
                151
            ],
            [
                189,
                171
            ],
            [
                189,
                172
            ],
            [
                189,
                188
            ],
            [
                189,
                218
            ],
            [
                189,
                219
            ],
            [
                189,
                234
            ],
            [
                189,
                235
            ],
            [
                190,
                48
            ],
            [
                190,
                152
            ],
            [
                190,
                153
            ],
            [
                190,
                154
            ],
            [
                190,
                168
            ],
            [
                190,
                169
            ],
            [
                190,
                170
            ],
            [
                190,
                189
            ],
            [
                190,
                217
            ],
            [
                191,
                48
            ],
            [
                191,
                155
            ],
            [
                191,
                156
            ],
            [
                191,
                160
            ],
            [
                191,
                161
            ],
            [
                191,
                162
            ],
            [
                191,
                163
            ],
            [
                191,
                164
            ],
            [
                191,
                165
            ],
            [
                191,
                166
            ],
            [
                191,
                167
            ],
            [
                191,
                189
            ],
            [
                191,
                216
            ],
            [
                192,
                48
            ],
            [
                192,
                190
            ],
            [
                192,
                216
            ],
            [
                193,
                48
            ],
            [
                193,
                158
            ],
            [
                193,
                190
            ],
            [
                193,
                215
            ],
            [
                194,
                48
            ],
            [
                194,
                158
            ],
            [
                194,
                191
            ],
            [
                194,
                214
            ],
            [
                195,
                48
            ],
            [
                195,
                158
            ],
            [
                195,
                191
            ],
            [
                195,
                213
            ],
            [
                196,
                48
            ],
            [
                196,
                159
            ],
            [
                196,
                192
            ],
            [
                196,
                212
            ],
            [
                197,
                48
            ],
            [
                197,
                159
            ],
            [
                197,
                193
            ],
            [
                197,
                211
            ],
            [
                198,
                48
            ],
            [
                198,
                160
            ],
            [
                198,
                194
            ],
            [
                198,
                210
            ],
            [
                199,
                48
            ],
            [
                199,
                160
            ],
            [
                199,
                195
            ],
            [
                199,
                209
            ],
            [
                200,
                49
            ],
            [
                200,
                161
            ],
            [
                200,
                196
            ],
            [
                200,
                197
            ],
            [
                200,
                198
            ],
            [
                200,
                206
            ],
            [
                200,
                207
            ],
            [
                200,
                208
            ],
            [
                201,
                49
            ],
            [
                201,
                162
            ],
            [
                201,
                199
            ],
            [
                201,
                200
            ],
            [
                201,
                201
            ],
            [
                201,
                202
            ],
            [
                201,
                203
            ],
            [
                201,
                204
            ],
            [
                201,
                205
            ],
            [
                202,
                49
            ],
            [
                202,
                163
            ],
            [
                203,
                49
            ],
            [
                203,
                164
            ],
            [
                203,
                165
            ],
            [
                204,
                49
            ],
            [
                204,
                166
            ],
            [
                205,
                49
            ],
            [
                205,
                167
            ],
            [
                206,
                50
            ],
            [
                206,
                168
            ],
            [
                207,
                50
            ],
            [
                207,
                169
            ],
            [
                207,
                170
            ],
            [
                208,
                50
            ],
            [
                208,
                171
            ],
            [
                209,
                50
            ],
            [
                209,
                172
            ],
            [
                210,
                51
            ],
            [
                210,
                173
            ],
            [
                211,
                52
            ],
            [
                211,
                174
            ],
            [
                211,
                175
            ],
            [
                212,
                53
            ],
            [
                212,
                176
            ],
            [
                213,
                54
            ],
            [
                213,
                177
            ],
            [
                213,
                178
            ],
            [
                213,
                179
            ],
            [
                214,
                55
            ],
            [
                214,
                180
            ],
            [
                214,
                181
            ],
            [
                215,
                56
            ],
            [
                215,
                57
            ],
            [
                215,
                182
            ],
            [
                215,
                183
            ],
            [
                215,
                199
            ],
            [
                215,
                200
            ],
            [
                215,
                201
            ],
            [
                215,
                202
            ],
            [
                215,
                203
            ],
            [
                215,
                204
            ],
            [
                215,
                205
            ],
            [
                215,
                206
            ],
            [
                215,
                207
            ],
            [
                215,
                208
            ],
            [
                216,
                58
            ],
            [
                216,
                184
            ],
            [
                216,
                195
            ],
            [
                216,
                196
            ],
            [
                216,
                197
            ],
            [
                216,
                198
            ],
            [
                216,
                209
            ],
            [
                217,
                59
            ],
            [
                217,
                185
            ],
            [
                217,
                186
            ],
            [
                217,
                187
            ],
            [
                217,
                188
            ],
            [
                217,
                189
            ],
            [
                217,
                190
            ],
            [
                217,
                191
            ],
            [
                217,
                192
            ],
            [
                217,
                193
            ],
            [
                217,
                194
            ],
            [
                217,
                210
            ],
            [
                218,
                60
            ],
            [
                218,
                211
            ],
            [
                219,
                61
            ],
            [
                219,
                212
            ],
            [
                220,
                62
            ],
            [
                220,
                212
            ],
            [
                221,
                63
            ],
            [
                221,
                213
            ],
            [
                222,
                63
            ],
            [
                222,
                213
            ],
            [
                223,
                62
            ],
            [
                223,
                213
            ],
            [
                224,
                62
            ],
            [
                224,
                213
            ],
            [
                225,
                61
            ],
            [
                225,
                213
            ],
            [
                226,
                60
            ],
            [
                226,
                213
            ],
            [
                227,
                59
            ],
            [
                227,
                213
            ],
            [
                228,
                56
            ],
            [
                228,
                57
            ],
            [
                228,
                58
            ],
            [
                228,
                213
            ],
            [
                229,
                52
            ],
            [
                229,
                53
            ],
            [
                229,
                54
            ],
            [
                229,
                55
            ],
            [
                229,
                213
            ],
            [
                230,
                213
            ],
            [
                231,
                213
            ],
            [
                232,
                213
            ],
            [
                233,
                213
            ],
            [
                234,
                212
            ],
            [
                235,
                212
            ],
            [
                236,
                211
            ],
            [
                237,
                209
            ],
            [
                237,
                210
            ],
            [
                238,
                208
            ]
        ]
    }
}